<?xml version="1.0" encoding="UTF-8"?>
<!-- http://5qx5fs.axshare.com/#p=t020_-_roleplay_prompted_reply -->
<!-- http://codebeautify.org/xmlviewer/c8556f -->
<assessmentItem identifier="" adaptive="false" title="" timeDependent="false" xmlns="http://www.imsglobal.org/xsd/imsqti_v2p1">
	<responseDeclaration identifier="MI1" cardinality="single" baseType="integer"/>
	<responseDeclaration identifier="MI2" cardinality="single" baseType="integer"/>
	<responseDeclaration identifier="MI3" cardinality="single" baseType="integer"/>
	<itemBody>
		<rubricBlock view="candidate">
			<div>Listen to Nina and record your lines in the conversation.</div>
		</rubricBlock>
		<infoControl title="hint">
			<div>Lorem ipsum dolor sit amet, consectetur adipiscing elit, sed do eiusmod tempor incididunt.</div>
		</infoControl>
		<div class="type:freetownpane width-100 spill shadow">
			<div class="type:carousel-vertical">
				<div class="type:carouselitem">
					<ul class="type:conversation role-play container">
						<li class="type:conversationitem media">
							<img class="type:avatar" alt="" src="../content/media/avatars/tom.png"/>
							<mediaInteraction class="type:video dialog" responseIdentifier="MI1" autostart="false">
								<object data="http://clips.vorwaerts-gmbh.de/big_buck_bunny.mp4" type="video/mp4" />
							</mediaInteraction>
						</li>
						<li class="type:conversationitem alternate">
							<img class="type:avatar blue" alt="" src="../content/media/avatars/kate.png"/>
							<p>
								Pea horseradish zuki bean lettuce avocado asparagus okra.
							</p>
						</li>
					</ul>
				</div>
				<div class="type:carouselitem">
					<ul class="type:conversation role-play container scrollable">
						<li class="type:conversationitem media">
							<img class="type:avatar" alt="" src="../content/media/avatars/tom.png"/>
							<mediaInteraction class="type:video dialog" responseIdentifier="MI2" autostart="false">
								<object data="http://clips.vorwaerts-gmbh.de/big_buck_bunny.mp4" type="video/mp4" />
							</mediaInteraction>
						</li>
						<li class="type:conversationitem alternate">
							<img class="type:avatar blue" alt="" src="../content/media/avatars/kate.png"/>
							<p>
								Pea horseradish zuki bean lettuce avocado asparagus okra.
							</p>
						</li>
					</ul>
				</div>
				<div class="type:carouselitem">
					<ul class="type:conversation role-play container scrollable">
						<li class="type:conversationitem media">
							<img class="type:avatar" alt="" src="../content/media/avatars/tom.png"/>
							<mediaInteraction class="type:video dialog" responseIdentifier="MI3" autostart="false">
								<object data="http://clips.vorwaerts-gmbh.de/big_buck_bunny.mp4" type="video/mp4" />
							</mediaInteraction>
						</li>
						<li class="type:conversationitem alternate">
							<img class="type:avatar blue" alt="" src="../content/media/avatars/kate.png"/>
							<p>
								Pea horseradish zuki bean lettuce avocado asparagus okra.
							</p>
						</li>
					</ul>
				</div>
			</div>
		</div>
	</itemBody>
</assessmentItem>